RapidUseML/RapidUseML.py
RapidUseML/__init__.py
RapidUseML-1.0.3.dist-info/METADATA
RapidUseML-1.0.3.dist-info/WHEEL
RapidUseML-1.0.3.dist-info/top_level.txt
RapidUseML-1.0.3.dist-info/RECORD
