Metadata-Version: 2.1
Name: RapidUseML
Version: 1.0.3
Summary: Minimalistic Machine Learning Toolset.
Author: 5krus (Eryk Krusinski)
Author-email: <eryk@krus.co.uk>
Keywords: machine learning,whittle laboratory
Classifier: Development Status :: 1 - Planning
Classifier: Intended Audience :: Developers
Classifier: Programming Language :: Python :: 3
Classifier: Operating System :: Unix
Classifier: Operating System :: MacOS :: MacOS X
Classifier: Operating System :: Microsoft :: Windows
Requires-Dist: pandas
Requires-Dist: joblib
Requires-Dist: numpy
Requires-Dist: scipy
Requires-Dist: scikit-learn
